logplus/__init__.py
logplus/_base.py
logplus/_config.py
logplus/_frames.py
logplus/_generic.py
logplus/_greenlets.py
logplus/_log_levels.py
logplus/_native.py
logplus/_output.py
logplus/_utils.py
logplus/cli.py
logplus/contextvars.py
logplus/dev.py
logplus/exceptions.py
logplus/processors.py
logplus/stdlib.py
logplus/testing.py
logplus/threadlocal.py
logplus/tracebacks.py
logplus/twisted.py
logplus/types.py
logplus/typing.py
logplus-0.1.3.dist-info/LICENSE
logplus-0.1.3.dist-info/METADATA
logplus-0.1.3.dist-info/WHEEL
logplus-0.1.3.dist-info/entry_points.txt
logplus-0.1.3.dist-info/top_level.txt
logplus-0.1.3.dist-info/RECORD
