Metadata-Version: 2.1
Name: logplus
Version: 0.1.3
Summary: Log Better
Home-page: https://github.com/tactlabs/logplus
Author: Raja CSP Raman
Author-email: info@tactii.com
License: MIT
Keywords: logplus
Classifier: Development Status :: 4 - Beta
Classifier: Intended Audience :: Developers
Classifier: License :: OSI Approved :: MIT License
Classifier: Programming Language :: Python :: 3.7
Requires-Python: >=3.7
License-File: LICENSE
Requires-Dist: pypandoc ==1.4
